Workbook

Sheet 00 Mode d'emploi
B2: PROSPECTION APPRENTISSAGE – SECTEUR PUBLIC, ÉCOLES ET SANTÉ
B3: Bassin Nord-Est de La Réunion : de Saint-Denis à Sainte-Rose, hauteurs comprises
B5: À QUOI SERT CE FICHIER
B6: Objectif | C6: Identifier les structures publiques, scolaires et de santé du bassin Nord-Est qui disposent d'un magasin, d'un économat, d'une cuisine centrale, d'une pharmacie ou d'un parc matériel — donc capables d'accueillir un(e) apprenti(e) opérateur logistique de 16 à 25 ans.
B7: Complémentaire du fichier privé | C7: Ce classeur est le pendant du fichier « Prospection_Logistique_Nord-Est_Reunion.xlsx » (entreprises privées). Même structure, mêmes colonnes, même méthode. Une seule structure figure dans les deux : le GHER à Saint-Benoît — ne l'appelez pas deux fois.
B8: Pourquoi ce gisement est sous-exploité | C8: Les CFA prospectent le privé et oublient le public. Or une mairie, un lycée ou un hôpital ont un magasin, des livraisons quotidiennes et des agents proches de la retraite à remplacer. La concurrence y est bien plus faible.
B10: ⚠️ À LIRE AVANT LE PREMIER APPEL
B11: Le public a un calendrier inversé | C11: Dans le privé, on prospecte pour la rentrée. Dans le public territorial, le financement de la formation par le CNFPT dépend d'un RECENSEMENT annuel qui se fait en début d'année civile. Une collectivité qui ne s'est pas recensée ne pourra pas être financée. Voir l'onglet « 09 Apprentissage dans le public » AVANT de décrocher le téléphone.
B12: Le bon interlocuteur n'est pas le maire | C12: Dans une commune : le DGS, la DRH et le directeur des services techniques. Dans un lycée : l'adjoint gestionnaire. Dans un hôpital : la direction des achats et de la logistique. Se tromper de porte fait perdre trois semaines.
B13: Fiabilité des données | C13: Les NOMS des structures sont publics et fiables. Les ADRESSES sont à confirmer (colonne « Fiabilité donnée »). SIRET, code APE et responsable portent « A VERIFIER » tant qu'ils n'ont pas été confirmés : aucune donnée n'a été inventée.
B15: REMPLISSAGE AUTOMATIQUE – 2 MINUTES
B16: Le script d'auto-complétion | C16: Le fichier « completer_via_annuaire.py » fonctionne aussi sur ce classeur : il interroge l'API officielle de l'INSEE et remplit SIRET, code APE, effectif et responsable. Les collectivités et les établissements publics sont bien présents dans cette base.
B17: Comment le lancer | C17: python3 completer_via_annuaire.py Prospection_Public_Sante_Nord-Est_Reunion.xlsx — voir LISEZ-MOI.md.
B19: LES ONGLETS
B20: 01 à 07 | C20: Un onglet par famille de structures. Les onglets 01 et 04 sont les plus gros gisements en nombre de postes ; les onglets 05 et 06 les plus gros en volume logistique par structure.
B21: 08 Pilotage | C21: Compteurs automatiques par onglet et par statut.
B22: 09 Apprentissage dans le public | C22: Qui finance quoi, le calendrier CNFPT, les pièces à déposer et les délais. C'est l'onglet qui fait la différence face à un DRH.
B23: 10 Script d'appel (public) | C23: Trame d'appel adaptée : on ne parle pas à une mairie comme à un transporteur.
B24: 11 Sources & mise à jour | C24: D'où viennent les données et où les actualiser.

Sheet 01 Communes & CCAS
A1: PROSPECTION PUBLIC & SANTÉ – COMMUNES & CCAS
A2: Les 9 communes du bassin et leurs CCAS – magasin communal, restauration scolaire, parc matériel
A4: N° | B4: Raison sociale / Enseigne | C4: Type de structure | D4: Adresse | E4: CP | F4: Commune | G4: SIRET (14 chiffres) | H4: Code APE | I4: Libellé APE | J4: Effectif (tranche INSEE) | K4: Dirigeant (Nom Prénom) | L4: Fonction | M4: Téléphone | N4: Email contact | O4: Site web | P4: Poste apprenti visé | Q4: Priorité | R4: Fiabilité donnée | S4: Vérifier SIRET / APE / Dirigeant | T4: Statut prospection | U4: Date dernier contact | V4: Notes
A5: 1 | B5: VILLE DE SAINT-DENIS | C5: Commune (fonction publique territoriale) | D5: 2 rue de Paris – Hôtel de Ville | E5: 97400 | F5: Saint-Denis | G5: A VERIFIER | H5: A VERIFIER | I5: A VERIFIER | J5: A COMPLETER | K5: A COMPLETER | L5: Dirigeant / DG | M5: A COMPLETER | N5: A COMPLETER | O5: A COMPLETER | P5: Magasinier / Magasin communal | Q5: P1 | R5: Source annuaire | S5: Ouvrir la fiche entreprise | T5: A contacter | V5: La plus grosse collectivité de l'île : magasin général, cuisines scolaires, parc matériel des fêtes et cérémonies, archives, parc automobile. Plusieurs postes d'apprentis logistique possibles la même année. Interlocuteurs : DGS + DRH + directeur des services techniques (c'est lui qui a le magasin).
A6: 2 | B6: CCAS DE SAINT-DENIS | C6: CCAS (établissement public communal) | D6: A VERIFIER | E6: 97400 | F6: Saint-Denis | G6: A VERIFIER | H6: A VERIFIER | I6: A VERIFIER | J6: A COMPLETER | K6: A COMPLETER | L6: Dirigeant / DG | M6: A COMPLETER | N6: A COMPLETER | O6: A COMPLETER | P6: Logistique de restauration collective | Q6: P2 | R6: Source annuaire | S6: Ouvrir la fiche entreprise | T6: A contacter | V6: Portage de repas à domicile, aide alimentaire, magasin de fournitures : flux quotidiens et gestion de stock du froid. Interlocuteur : directeur du CCAS.
A7: 3 | B7: VILLE DE SAINTE-MARIE | C7: Commune (fonction publique territoriale) | D7: A VERIFIER | E7: 97438 | F7: Sainte-Marie | G7: A VERIFIER | H7: A VERIFIER | I7: A VERIFIER | J7: A COMPLETER | K7: A COMPLETER | L7: Dirigeant / DG | M7: A COMPLETER | N7: A COMPLETER | O7: A COMPLETER | P7: Magasinier / Magasin communal | Q7: P1 | R7: A vérifier | S7: Ouvrir la fiche entreprise | T7: A contacter | V7: Commune en croissance, zone aéroportuaire sur son territoire. Magasin communal, restauration scolaire, services techniques. Interlocuteurs : DGS + DRH + directeur des services techniques (c'est lui qui a le magasin).
A8: 4 | B8: CCAS DE SAINTE-MARIE | C8: CCAS (établissement public communal) | D8: A VERIFIER | E8: 97438 | F8: Sainte-Marie | G8: A VERIFIER | H8: A VERIFIER | I8: A VERIFIER | J8: A COMPLETER | K8: A COMPLETER | L8: Dirigeant / DG | M8: A COMPLETER | N8: A COMPLETER | O8: A COMPLETER | P8: Logistique de restauration collective | Q8: P3 | R8: A vérifier | S8: Ouvrir la fiche entreprise | T8: A contacter | V8: Portage de repas et aide sociale : vérifier le volume avant de proposer un apprenti.
A9: 5 | B9: VILLE DE SAINTE-SUZANNE | C9: Commune (fonction publique territoriale) | D9: A VERIFIER | E9: 97441 | F9: Sainte-Suzanne | G9: A VERIFIER | H9: A VERIFIER | I9: A VERIFIER | J9: A COMPLETER | K9: A COMPLETER | L9: Dirigeant / DG | M9: A COMPLETER | N9: A COMPLETER | O9: A COMPLETER | P9: Magasinier / Magasin communal | Q9: P2 | R9: A vérifier | S9: Ouvrir la fiche entreprise | T9: A contacter | V9: Commune de taille moyenne : un seul magasin, mais un tuteur facile à identifier. Interlocuteurs : DGS + DRH + directeur des services techniques (c'est lui qui a le magasin).
A10: 6 | B10: VILLE DE SAINT-ANDRÉ | C10: Commune (fonction publique territoriale) | D10: A VERIFIER | E10: 97440 | F10: Saint-André | G10: A VERIFIER | H10: A VERIFIER | I10: A VERIFIER | J10: A COMPLETER | K10: A COMPLETER | L10: Dirigeant / DG | M10: A COMPLETER | N10: A COMPLETER | O10: A COMPLETER | P10: Magasinier / Magasin communal | Q10: P1 | R10: A vérifier | S10: Ouvrir la fiche entreprise | T10: A contacter | V10: 2e ville de l'Est. Restauration scolaire importante, services techniques étoffés, magasin communal. Cible prioritaire du bassin Est. Interlocuteurs : DGS + DRH + directeur des services techniques (c'est lui qui a le magasin).
A11: 7 | B11: CCAS DE SAINT-ANDRÉ | C11: CCAS (établissement public communal) | D11: A VERIFIER | E11: 97440 | F11: Saint-André | G11: A VERIFIER | H11: A VERIFIER | I11: A VERIFIER | J11: A COMPLETER | K11: A COMPLETER | L11: Dirigeant / DG | M11: A COMPLETER | N11: A COMPLETER | O11: A COMPLETER | P11: Logistique de restauration collective | Q11: P2 | R11: A vérifier | S11: Ouvrir la fiche entreprise | T11: A contacter | V11: Action sociale et portage de repas sur un bassin de population important.
A12: 8 | B12: VILLE DE BRAS-PANON | C12: Commune (fonction publique territoriale) | D12: A VERIFIER | E12: 97412 | F12: Bras-Panon | G12: A VERIFIER | H12: A VERIFIER | I12: A VERIFIER | J12: A COMPLETER | K12: A COMPLETER | L12: Dirigeant / DG | M12: A COMPLETER | N12: A COMPLETER | O12: A COMPLETER | P12: Magasinier / Magasin communal | Q12: P2 | R12: A vérifier | S12: Ouvrir la fiche entreprise | T12: A contacter | V12: Petite commune : le maire et le DGS décident vite. Magasin et parc matériel. Interlocuteurs : DGS + DRH + directeur des services techniques (c'est lui qui a le magasin).
A13: 9 | B13: VILLE DE SAINT-BENOÎT | C13: Commune (fonction publique territoriale) | D13: A VERIFIER | E13: 97470 | F13: Saint-Benoît | G13: A VERIFIER | H13: A VERIFIER | I13: A VERIFIER | J13: A COMPLETER | K13: A COMPLETER | L13: Dirigeant / DG | M13: A COMPLETER | N13: A COMPLETER | O13: A COMPLETER | P13: Magasinier / Magasin communal | Q13: P1 | R13: A vérifier | S13: Ouvrir la fiche entreprise | T13: A contacter | V13: Ville-centre de l'Est, siège de la CIREST. Services techniques, restauration scolaire, magasin. Interlocuteurs : DGS + DRH + directeur des services techniques (c'est lui qui a le magasin).
A14: 10 | B14: VILLE DE LA PLAINE-DES-PALMISTES | C14: Commune (fonction publique territoriale) | D14: A VERIFIER | E14: 97431 | F14: La Plaine-des-Palmistes | G14: A VERIFIER | H14: A VERIFIER | I14: A VERIFIER | J14: A COMPLETER | K14: A COMPLETER | L14: Dirigeant / DG | M14: A COMPLETER | N14: A COMPLETER | O14: A COMPLETER | P14: Magasinier / Magasin communal | Q14: P3 | R14: A vérifier | S14: Ouvrir la fiche entreprise | T14: A contacter | V14: Commune des hauteurs, effectifs réduits : viser un poste polyvalent magasin + régie. Vérifier qu'un tuteur est disponible.
A15: 11 | B15: VILLE DE SAINTE-ROSE | C15: Commune (fonction publique territoriale) | D15: A VERIFIER | E15: 97439 | F15: Sainte-Rose | G15: A VERIFIER | H15: A VERIFIER | I15: A VERIFIER | J15: A COMPLETER | K15: A COMPLETER | L15: Dirigeant / DG | M15: A COMPLETER | N15: A COMPLETER | O15: A COMPLETER | P15: Magasinier / Magasin communal | Q15: P3 | R15: A vérifier | S15: Ouvrir la fiche entreprise | T15: A contacter | V15: Commune la plus éloignée du bassin : c'est souvent le SEUL employeur structuré de la commune. Argument fort pour un jeune du secteur qui ne peut pas se déplacer.
A16: 12 | B16: VILLE DE SALAZIE | C16: Commune (fonction publique territoriale) | D16: A VERIFIER | E16: 97433 | F16: Salazie | G16: A VERIFIER | H16: A VERIFIER | I16: A VERIFIER | J16: A COMPLETER | K16: A COMPLETER | L16: Dirigeant / DG | M16: A COMPLETER | N16: A COMPLETER | O16: A COMPLETER | P16: Magasinier / Magasin communal | Q16: P3 | R16: A vérifier | S16: Ouvrir la fiche entreprise | T16: A contacter | V16: Cirque de Salazie : mobilité très contrainte pour les jeunes. La mairie est le principal employeur local. Même argument que Sainte-Rose.

Sheet 02 Intercommunalités
A1: PROSPECTION PUBLIC & SANTÉ – INTERCOMMUNALITÉS
A2: CIREST, CINOR et syndicats – déchets, transports, ateliers et magasins
A4: N° | B4: Raison sociale / Enseigne | C4: Type de structure | D4: Adresse | E4: CP | F4: Commune | G4: SIRET (14 chiffres) | H4: Code APE | I4: Libellé APE | J4: Effectif (tranche INSEE) | K4: Dirigeant (Nom Prénom) | L4: Fonction | M4: Téléphone | N4: Email contact | O4: Site web | P4: Poste apprenti visé | Q4: Priorité | R4: Fiabilité donnée | S4: Vérifier SIRET / APE / Dirigeant | T4: Statut prospection | U4: Date dernier contact | V4: Notes
A5: 1 | B5: CIREST – COMMUNAUTÉ INTERCOMMUNALE RÉUNION EST | C5: Intercommunalité (EPCI) | D5: A VERIFIER | E5: 97437 | F5: Saint-Benoît | G5: A VERIFIER | H5: A VERIFIER | I5: A VERIFIER | J5: A COMPLETER | K5: A COMPLETER | L5: Dirigeant / DG | M5: A COMPLETER | N5: A COMPLETER | O5: https://www.cirest.fr/ | P5: Magasinier / Gestion des stocks | Q5: P1 | R5: Source annuaire | S5: Ouvrir la fiche entreprise | T5: A contacter | V5: Regroupe 6 communes : Bras-Panon, La Plaine-des-Palmistes, Saint-André, Saint-Benoît, Sainte-Rose et Salazie. SIREN relevé sur l'Annuaire des Entreprises : 249740093 (le SIRET du siège reste à récupérer). Compétences déchets, transport, eau : magasins, ateliers et flux de matériel.
A6: 2 | B6: CINOR – COMMUNAUTÉ INTERCOMMUNALE DU NORD DE LA RÉUNION | C6: Intercommunalité (EPCI) | D6: A VERIFIER | E6: 97400 | F6: Saint-Denis | G6: A VERIFIER | H6: A VERIFIER | I6: A VERIFIER | J6: A COMPLETER | K6: A COMPLETER | L6: Dirigeant / DG | M6: A COMPLETER | N6: A COMPLETER | O6: A COMPLETER | P6: Magasinier / Gestion des stocks | Q6: P1 | R6: Source annuaire | S6: Ouvrir la fiche entreprise | T6: A contacter | V6: Regroupe Saint-Denis, Sainte-Marie et Sainte-Suzanne. Compétences déchets, transports, développement économique : ateliers, magasins, parc de bacs et de conteneurs à gérer.
A7: 3 | B7: SYDNE – SYNDICAT MIXTE DE TRAITEMENT DES DÉCHETS | C7: Syndicat mixte | D7: A VERIFIER | E7: 97400 | F7: Saint-Denis | G7: A VERIFIER | H7: A VERIFIER | I7: A VERIFIER | J7: A COMPLETER | K7: A COMPLETER | L7: Dirigeant / DG | M7: A COMPLETER | N7: A COMPLETER | O7: A COMPLETER | P7: Opérateur logistique / Prépa. commandes | Q7: P2 | R7: A vérifier | S7: Ouvrir la fiche entreprise | T7: A contacter | V7: Syndicat de traitement des déchets porté par la CINOR et la CIREST. Flux, pesée, quais de transfert : environnement logistique réel. Confirmer le siège et la commune avant l'appel.
A8: 4 | B8: SIDELEC RÉUNION | C8: Syndicat intercommunal d'électricité | D8: A VERIFIER | E8: 97400 | F8: Saint-Denis | G8: A VERIFIER | H8: A VERIFIER | I8: A VERIFIER | J8: A COMPLETER | K8: A COMPLETER | L8: Dirigeant / DG | M8: A COMPLETER | N8: A COMPLETER | O8: A COMPLETER | P8: Magasinier atelier / Parc matériel | Q8: P3 | R8: A vérifier | S8: Ouvrir la fiche entreprise | T8: A contacter | V8: Syndicat d'électrification : magasin de matériel électrique et parc. Vérifier l'existence d'un magasin propre avant de prospecter.

Sheet 03 Département, Région & État
A1: PROSPECTION PUBLIC & SANTÉ – DÉPARTEMENT, RÉGION & ÉTAT
A2: Département, Région, Rectorat, Université, CROUS, SDIS – les gros employeurs publics
A4: N° | B4: Raison sociale / Enseigne | C4: Type de structure | D4: Adresse | E4: CP | F4: Commune | G4: SIRET (14 chiffres) | H4: Code APE | I4: Libellé APE | J4: Effectif (tranche INSEE) | K4: Dirigeant (Nom Prénom) | L4: Fonction | M4: Téléphone | N4: Email contact | O4: Site web | P4: Poste apprenti visé | Q4: Priorité | R4: Fiabilité donnée | S4: Vérifier SIRET / APE / Dirigeant | T4: Statut prospection | U4: Date dernier contact | V4: Notes
A5: 1 | B5: CONSEIL DÉPARTEMENTAL DE LA RÉUNION | C5: Département (collectivité) | D5: 2 rue de la Source – Hôtel du Département | E5: 97400 | F5: Saint-Denis | G5: A VERIFIER | H5: A VERIFIER | I5: A VERIFIER | J5: A COMPLETER | K5: A COMPLETER | L5: Dirigeant / DG | M5: A COMPLETER | N5: A COMPLETER | O5: A COMPLETER | P5: Magasinier / Gestion des stocks | Q5: P1 | R5: Source annuaire | S5: Ouvrir la fiche entreprise | T5: A contacter | V5: Très gros employeur territorial. Gère les COLLÈGES (restauration et matériel), les routes départementales, l'action sociale : magasins, économats et parcs sur tout le territoire, y compris à l'Est. Passer par la DRH ET la direction de la logistique / des moyens généraux.
A6: 2 | B6: RÉGION RÉUNION | C6: Région (collectivité) | D6: Avenue René Cassin – Moufia, Hôtel de Région Pierre Lagourgue | E6: 97490 | F6: Sainte-Clotilde (Saint-Denis) | G6: A VERIFIER | H6: A VERIFIER | I6: A VERIFIER | J6: A COMPLETER | K6: A COMPLETER | L6: Dirigeant / DG | M6: A COMPLETER | N6: A COMPLETER | O6: A COMPLETER | P6: Magasinier / Gestion des stocks | Q6: P1 | R6: Source annuaire | S6: Ouvrir la fiche entreprise | T6: A contacter | V6: Gère les LYCÉES (restauration, équipement, maintenance) et les grandes infrastructures. Deux portes d'entrée : les moyens généraux de la Région, et chaque lycée pris individuellement (voir onglet 04).
A7: 3 | B7: RECTORAT DE L'ACADÉMIE DE LA RÉUNION | C7: État (éducation nationale) | D7: 24 avenue Georges Brassens – Le Moufia | E7: 97490 | F7: Sainte-Clotilde (Saint-Denis) | G7: A VERIFIER | H7: A VERIFIER | I7: A VERIFIER | J7: A COMPLETER | K7: A COMPLETER | L7: Dirigeant / DG | M7: A COMPLETER | N7: A COMPLETER | O7: A COMPLETER | P7: Agent d'économat / Réception-stocks | Q7: P2 | R7: Source annuaire | S7: Ouvrir la fiche entreprise | T7: A contacter | V7: Fonction publique d'État : apprentissage possible. Services logistiques, reprographie, magasin. Ouvre surtout la porte des lycées et collèges du bassin.
A8: 4 | B8: UNIVERSITÉ DE LA RÉUNION | C8: Établissement public d'enseignement supérieur | D8: 15 avenue René Cassin – Campus du Moufia | E8: 97490 | F8: Sainte-Clotilde (Saint-Denis) | G8: A VERIFIER | H8: A VERIFIER | I8: A VERIFIER | J8: A COMPLETER | K8: A COMPLETER | L8: Dirigeant / DG | M8: A COMPLETER | N8: A COMPLETER | O8: A COMPLETER | P8: Magasinier / Gestion des stocks | Q8: P2 | R8: Source annuaire | S8: Ouvrir la fiche entreprise | T8: A contacter | V8: Magasin central, laboratoires, reprographie, logistique de campus. Structure habituée à l'alternance : dossier administratif bien rodé.
A9: 5 | B9: CROUS DE LA RÉUNION | C9: Établissement public (vie étudiante) | D9: A VERIFIER | E9: 97490 | F9: Sainte-Clotilde (Saint-Denis) | G9: A VERIFIER | H9: A VERIFIER | I9: A VERIFIER | J9: A COMPLETER | K9: A COMPLETER | L9: Dirigeant / DG | M9: A COMPLETER | N9: A COMPLETER | O9: A COMPLETER | P9: Logistique de restauration collective | Q9: P2 | R9: A vérifier | S9: Ouvrir la fiche entreprise | T9: A contacter | V9: Restauration universitaire et résidences : réception de denrées, gestion de stocks, approvisionnement de plusieurs points de vente. Vrai métier logistique.
A10: 6 | B10: SDIS 974 – SERVICE D'INCENDIE ET DE SECOURS | C10: Établissement public territorial | D10: A VERIFIER | E10: 97400 | F10: Saint-Denis | G10: A VERIFIER | H10: A VERIFIER | I10: A VERIFIER | J10: A COMPLETER | K10: A COMPLETER | L10: Dirigeant / DG | M10: A COMPLETER | N10: A COMPLETER | O10: A COMPLETER | P10: Magasinier / Gestion des stocks | Q10: P1 | R10: A vérifier | S10: Ouvrir la fiche entreprise | T10: A contacter | V10: Magasin d'habillement, magasin de matériel de secours, pharmacie, parc de véhicules, approvisionnement de tous les centres de secours du département. L'un des plus beaux terrains logistiques du public. Confirmer l'adresse de l'état-major et le service en charge de la logistique.

Sheet 04 Lycées & collèges
A1: PROSPECTION PUBLIC & SANTÉ – LYCÉES & COLLÈGES
A2: EPLE du bassin – magasin d'intendance et restauration scolaire (voir l'adjoint gestionnaire)
A4: N° | B4: Raison sociale / Enseigne | C4: Type de structure | D4: Adresse | E4: CP | F4: Commune | G4: SIRET (14 chiffres) | H4: Code APE | I4: Libellé APE | J4: Effectif (tranche INSEE) | K4: Dirigeant (Nom Prénom) | L4: Fonction | M4: Téléphone | N4: Email contact | O4: Site web | P4: Poste apprenti visé | Q4: Priorité | R4: Fiabilité donnée | S4: Vérifier SIRET / APE / Dirigeant | T4: Statut prospection | U4: Date dernier contact | V4: Notes
A5: 1 | B5: LYCÉE LISLET GEOFFROY | C5: Lycée (EPLE) | D5: A VERIFIER | E5: 97490 | F5: Sainte-Clotilde (Saint-Denis) | G5: A VERIFIER | H5: A VERIFIER | I5: A VERIFIER | J5: A COMPLETER | K5: A COMPLETER | L5: Dirigeant / DG | M5: A COMPLETER | N5: A COMPLETER | O5: A COMPLETER | P5: Agent d'économat / Réception-stocks | Q5: P1 | R5: Source annuaire | S5: Ouvrir la fiche entreprise | T5: A contacter | V5: Magasin d'intendance et restauration scolaire. Interlocuteur : l'ADJOINT GESTIONNAIRE (intendant). C'est lui qui gère le magasin et la restauration ; le chef d'établissement signe.
A6: 2 | B6: LYCÉE SARDA GARRIGA | C6: Lycée (EPLE) | D6: A VERIFIER | E6: 97440 | F6: Saint-André | G6: A VERIFIER | H6: A VERIFIER | I6: A VERIFIER | J6: A COMPLETER | K6: A COMPLETER | L6: Dirigeant / DG | M6: A COMPLETER | N6: A COMPLETER | O6: A COMPLETER | P6: Agent d'économat / Réception-stocks | Q6: P1 | R6: Source annuaire | S6: Ouvrir la fiche entreprise | T6: A contacter | V6: Gros établissement de l'Est : réception de denrées quotidienne, magasin, gestion des manuels et des équipements. Interlocuteur : l'ADJOINT GESTIONNAIRE (intendant). C'est lui qui gère le magasin et la restauration ; le chef d'établissement signe.
A7: 3 | B7: LYCÉE MAHATMA GANDHI | C7: Lycée (EPLE) | D7: A VERIFIER | E7: 97440 | F7: Saint-André | G7: A VERIFIER | H7: A VERIFIER | I7: A VERIFIER | J7: A COMPLETER | K7: A COMPLETER | L7: Dirigeant / DG | M7: A COMPLETER | N7: A COMPLETER | O7: A COMPLETER | P7: Agent d'économat / Réception-stocks | Q7: P2 | R7: Source annuaire | S7: Ouvrir la fiche entreprise | T7: A contacter | V7: Restauration scolaire et magasin. Interlocuteur : l'ADJOINT GESTIONNAIRE (intendant). C'est lui qui gère le magasin et la restauration ; le chef d'établissement signe.
A8: 4 | B8: LYCÉE AMIRAL PIERRE BOUVET | C8: Lycée (EPLE) | D8: A VERIFIER | E8: 97470 | F8: Saint-Benoît | G8: A VERIFIER | H8: A VERIFIER | I8: A VERIFIER | J8: A COMPLETER | K8: A COMPLETER | L8: Dirigeant / DG | M8: A COMPLETER | N8: A COMPLETER | O8: A COMPLETER | P8: Agent d'économat / Réception-stocks | Q8: P1 | R8: Source annuaire | S8: Ouvrir la fiche entreprise | T8: A contacter | V8: Établissement de référence de Saint-Benoît. Interlocuteur : l'ADJOINT GESTIONNAIRE (intendant). C'est lui qui gère le magasin et la restauration ; le chef d'établissement signe.
A9: 5 | B9: LYCÉE DE BRAS-FUSIL | C9: Lycée professionnel (EPLE) | D9: A VERIFIER | E9: 97470 | F9: Saint-Benoît | G9: A VERIFIER | H9: A VERIFIER | I9: A VERIFIER | J9: A COMPLETER | K9: A COMPLETER | L9: Dirigeant / DG | M9: A COMPLETER | N9: A COMPLETER | O9: A COMPLETER | P9: Agent d'économat / Réception-stocks | Q9: P1 | R9: Source annuaire | S9: Ouvrir la fiche entreprise | T9: A contacter | V9: Lycée professionnel : la culture de l'alternance y est déjà installée, l'accueil d'un apprenti y est plus naturel. Interlocuteur : l'ADJOINT GESTIONNAIRE (intendant). C'est lui qui gère le magasin et la restauration ; le chef d'établissement signe.
A10: 6 | B10: AUTRES LYCÉES ET COLLÈGES DU BASSIN | C10: Établissements scolaires – à lister | D10: Annuaire de l'éducation (data.education.gouv.fr) filtré sur les communes du bassin | E10: 97400 | F10: Bassin Nord-Est | G10: A VERIFIER | H10: A VERIFIER | I10: A VERIFIER | J10: A COMPLETER | K10: A COMPLETER | L10: Dirigeant / DG | M10: A COMPLETER | N10: A COMPLETER | O10: A COMPLETER | P10: Agent d'économat / Réception-stocks | Q10: P2 | R10: A vérifier | S10: Ouvrir la fiche entreprise | T10: A contacter | V10: Chaque collège et lycée a un adjoint gestionnaire, une demi-pension et un magasin. C'est un gisement de postes très peu prospecté par les CFA. Méthode : annuaire de l'éducation, filtre commune, puis appel direct à l'intendance.

Sheet 05 Hôpital public
A1: PROSPECTION PUBLIC & SANTÉ – HÔPITAL PUBLIC
A2: CHU site Félix Guyon, GHER – magasin général, pharmacie à usage intérieur, plateforme
A4: N° | B4: Raison sociale / Enseigne | C4: Type de structure | D4: Adresse | E4: CP | F4: Commune | G4: SIRET (14 chiffres) | H4: Code APE | I4: Libellé APE | J4: Effectif (tranche INSEE) | K4: Dirigeant (Nom Prénom) | L4: Fonction | M4: Téléphone | N4: Email contact | O4: Site web | P4: Poste apprenti visé | Q4: Priorité | R4: Fiabilité donnée | S4: Vérifier SIRET / APE / Dirigeant | T4: Statut prospection | U4: Date dernier contact | V4: Notes
A5: 1 | B5: CHU DE LA RÉUNION – SITE FÉLIX GUYON | C5: CHU (fonction publique hospitalière) | D5: Allée des Topazes – Bellepierre | E5: 97400 | F5: Saint-Denis | G5: A VERIFIER | H5: A VERIFIER | I5: A VERIFIER | J5: A COMPLETER | K5: A COMPLETER | L5: Dirigeant / DG | M5: A COMPLETER | N5: A COMPLETER | O5: https://www.chu-reunion.fr/ | P5: Logistique pharmaceutique / PUI | Q5: P1 | R5: Source annuaire | S5: Ouvrir la fiche entreprise | T5: A contacter | V5: LE plus gros employeur logistique du Nord : magasin général, plateforme de distribution interne, pharmacie à usage intérieur, blanchisserie, restauration, brancardage. Le CHU dispose d'une Direction des Achats et de la Logistique (Nord). Interlocuteurs : direction des achats et de la logistique + DRH. Le cadre du magasin général est le prescripteur.
A6: 2 | B6: GROUPE HOSPITALIER EST RÉUNION (GHER) | C6: Hôpital public (FPH) | D6: 30 RN3 – ZAC Madeleine, Bras-Fusil | E6: 97470 | F6: Saint-Benoît | G6: A VERIFIER | H6: A VERIFIER | I6: A VERIFIER | J6: A COMPLETER | K6: A COMPLETER | L6: Dirigeant / DG | M6: A COMPLETER | N6: A COMPLETER | O6: A COMPLETER | P6: Logistique pharmaceutique / PUI | Q6: P1 | R6: Source annuaire | S6: Ouvrir la fiche entreprise | T6: A contacter | V6: Hôpital de référence de l'Est : magasin général, pharmacie, restauration. ATTENTION : cette structure figure aussi dans le fichier logistique privée — ne passez pas deux appels séparés. Interlocuteurs : direction des achats et de la logistique + DRH. Le cadre du magasin général est le prescripteur.
A7: 3 | B7: EPSMR – ÉTABLISSEMENT PUBLIC DE SANTÉ MENTALE | C7: Hôpital public (FPH) – hors bassin | D7: A VERIFIER | E7: 97460 | F7: Saint-Paul | G7: A VERIFIER | H7: A VERIFIER | I7: A VERIFIER | J7: A COMPLETER | K7: A COMPLETER | L7: Dirigeant / DG | M7: A COMPLETER | N7: A COMPLETER | O7: A COMPLETER | P7: Magasinier / Gestion des stocks | Q7: P3 | R7: A vérifier | S7: Ouvrir la fiche entreprise | T7: A contacter | V7: HORS BASSIN Nord-Est : à ne proposer qu'à un candidat mobile et véhiculé. Confirmer le site avant tout contact.

Sheet 06 Cliniques & santé privée
A1: PROSPECTION PUBLIC & SANTÉ – CLINIQUES & SANTÉ PRIVÉE
A2: Groupe Clinifutur et cliniques du Nord-Est – PUI, dispositifs médicaux, logistique hôtelière
A4: N° | B4: Raison sociale / Enseigne | C4: Type de structure | D4: Adresse | E4: CP | F4: Commune | G4: SIRET (14 chiffres) | H4: Code APE | I4: Libellé APE | J4: Effectif (tranche INSEE) | K4: Dirigeant (Nom Prénom) | L4: Fonction | M4: Téléphone | N4: Email contact | O4: Site web | P4: Poste apprenti visé | Q4: Priorité | R4: Fiabilité donnée | S4: Vérifier SIRET / APE / Dirigeant | T4: Statut prospection | U4: Date dernier contact | V4: Notes
A5: 1 | B5: CLINIQUE SAINTE-CLOTILDE (GROUPE CLINIFUTUR) | C5: Clinique privée MCO | D5: 127 route de Bois de Nèfles – Sainte-Clotilde | E5: 97490 | F5: Sainte-Clotilde (Saint-Denis) | G5: A VERIFIER | H5: A VERIFIER | I5: A VERIFIER | J5: A COMPLETER | K5: A COMPLETER | L5: Dirigeant / DG | M5: A COMPLETER | N5: A COMPLETER | O5: https://www.clinifutur.net/ | P5: Logistique pharmaceutique / PUI | Q5: P1 | R5: Source annuaire | S5: Ouvrir la fiche entreprise | T5: A contacter | V5: Environ 650 salariés et 100 médecins : la plus grande clinique de l'île et le plus gros plateau chirurgical privé du Nord-Est. Pharmacie à usage intérieur, magasin de dispositifs médicaux, logistique hôtelière et restauration. Interlocuteurs : DRH + pharmacien gérant + responsable des services économiques.
A6: 2 | B6: GROUPE DE SANTÉ CLINIFUTUR – direction | C6: Groupe de santé privé (siège) | D6: A VERIFIER | E6: 97490 | F6: Sainte-Clotilde (Saint-Denis) | G6: A VERIFIER | H6: A VERIFIER | I6: A VERIFIER | J6: A COMPLETER | K6: A COMPLETER | L6: Dirigeant / DG | M6: A COMPLETER | N6: A COMPLETER | O6: A COMPLETER | P6: Magasinier / Gestion des stocks | Q6: P1 | R6: Source annuaire | S6: Ouvrir la fiche entreprise | T6: A contacter | V6: Le groupe exploite plusieurs cliniques à La Réunion et à Mayotte (Sainte-Clotilde, La Paix, Les Oliviers, Robert Debré, Saint-Joseph, Saint-Vincent) ainsi que les centres de dialyse SODIA. Un accord au niveau du groupe peut ouvrir plusieurs sites d'un coup : c'est le meilleur rapport effort / résultat de cet onglet.
A7: 3 | B7: SODIA RÉUNION (dialyse – groupe Clinifutur) | C7: Dialyse / Santé privée | D7: A VERIFIER | E7: 97490 | F7: Sainte-Clotilde (Saint-Denis) | G7: A VERIFIER | H7: A VERIFIER | I7: A VERIFIER | J7: A COMPLETER | K7: A COMPLETER | L7: Dirigeant / DG | M7: A COMPLETER | N7: A COMPLETER | O7: A COMPLETER | P7: Opérateur logistique / Prépa. commandes | Q7: P2 | R7: A vérifier | S7: Ouvrir la fiche entreprise | T7: A contacter | V7: Centres de dialyse : consommables, poches, filtres, livraisons sur plusieurs sites. Logistique du soin très normée. Confirmer les sites du bassin Nord-Est.
A8: 4 | B8: AUTRES CLINIQUES DU GROUPE (La Paix, Les Oliviers, Robert Debré, Saint-Joseph, Saint-Vincent) | C8: Cliniques privées – à lister | D8: A VERIFIER | E8: 97400 | F8: À vérifier | G8: A VERIFIER | H8: A VERIFIER | I8: A VERIFIER | J8: A COMPLETER | K8: A COMPLETER | L8: Dirigeant / DG | M8: A COMPLETER | N8: A COMPLETER | O8: A COMPLETER | P8: Magasinier / Gestion des stocks | Q8: P3 | R8: A vérifier | S8: Ouvrir la fiche entreprise | T8: A contacter | V8: Ces cliniques existent, mais TOUTES ne sont pas dans le bassin Nord-Est. Vérifiez la commune de chacune avant de les intégrer à votre tournée.

Sheet 07 EHPAD & médico-social
A1: PROSPECTION PUBLIC & SANTÉ – EHPAD & MÉDICO-SOCIAL
A2: AURAR, EHPAD, ESAT – petites structures, décision rapide, un apprenti chacune
A4: N° | B4: Raison sociale / Enseigne | C4: Type de structure | D4: Adresse | E4: CP | F4: Commune | G4: SIRET (14 chiffres) | H4: Code APE | I4: Libellé APE | J4: Effectif (tranche INSEE) | K4: Dirigeant (Nom Prénom) | L4: Fonction | M4: Téléphone | N4: Email contact | O4: Site web | P4: Poste apprenti visé | Q4: Priorité | R4: Fiabilité donnée | S4: Vérifier SIRET / APE / Dirigeant | T4: Statut prospection | U4: Date dernier contact | V4: Notes
A5: 1 | B5: AURAR – UNITÉ DE SAINT-BENOÎT | C5: Dialyse / Association de santé | D5: 1 rue des Aubépines | E5: 97470 | F5: Saint-Benoît | G5: A VERIFIER | H5: A VERIFIER | I5: A VERIFIER | J5: A COMPLETER | K5: A COMPLETER | L5: Dirigeant / DG | M5: 0262 98 98 98 | N5: A COMPLETER | O5: https://aurar.fr/nous-trouver/ | P5: Opérateur logistique / Prépa. commandes | Q5: P1 | R5: Source annuaire | S5: Ouvrir la fiche entreprise | T5: A contacter | V5: Centre lourd, dialyse médicalisée et auto-dialyse. Téléphone relevé en source publique, à reconfirmer. Approvisionnement en consommables et gestion de stock sur site : poste d'apprenti tout à fait tenable.
A6: 2 | B6: AURAR – AUTRES UNITÉS DU NORD-EST | C6: Dialyse / Association de santé | D6: A VERIFIER | E6: 97490 | F6: Sainte-Clotilde (Saint-Denis) | G6: A VERIFIER | H6: A VERIFIER | I6: A VERIFIER | J6: A COMPLETER | K6: A COMPLETER | L6: Dirigeant / DG | M6: A COMPLETER | N6: A COMPLETER | O6: A COMPLETER | P6: Opérateur logistique / Prépa. commandes | Q6: P2 | R6: Source annuaire | S6: Ouvrir la fiche entreprise | T6: A contacter | V6: L'AURAR est présente dans l'Est, le Nord, l'Ouest et le Sud. Une seule négociation avec le siège peut couvrir plusieurs unités du bassin.
A7: 3 | B7: EHPAD DU BASSIN NORD-EST | C7: EHPAD – à lister | D7: Annuaire sante.fr / FINESS, filtre communes du bassin | E7: 97400 | F7: Bassin Nord-Est | G7: A VERIFIER | H7: A VERIFIER | I7: A VERIFIER | J7: A COMPLETER | K7: A COMPLETER | L7: Dirigeant / DG | M7: A COMPLETER | N7: A COMPLETER | O7: A COMPLETER | P7: Logistique de restauration collective | Q7: P2 | R7: A vérifier | S7: Ouvrir la fiche entreprise | T7: A contacter | V7: Chaque EHPAD a une cuisine, une lingerie, un magasin de protections et de matériel médical. Structures petites mais nombreuses : un apprenti par EHPAD, et le directeur décide seul. Méthode : sante.fr, filtre EHPAD + commune.
A8: 4 | B8: ESAT ET ÉTABLISSEMENTS MÉDICO-SOCIAUX DU BASSIN | C8: ESAT / IME / Foyers – à lister | D8: A VERIFIER | E8: 97400 | F8: Bassin Nord-Est | G8: A VERIFIER | H8: A VERIFIER | I8: A VERIFIER | J8: A COMPLETER | K8: A COMPLETER | L8: Dirigeant / DG | M8: A COMPLETER | N8: A COMPLETER | O8: A COMPLETER | P8: Opérateur logistique / Prépa. commandes | Q8: P2 | R8: A vérifier | S8: Ouvrir la fiche entreprise | T8: A contacter | V8: Les ESAT ont souvent des ateliers de conditionnement, de tri et de logistique : l'apprenti y encadre et organise le flux. Double intérêt : poste logistique réel et forte adhésion des directions à la démarche d'insertion.

Sheet 08 Pilotage
A1: PILOTAGE DE LA CAMPAGNE – PUBLIC & SANTÉ
A2: Compteurs automatiques – se mettent à jour quand vous remplissez les onglets 01 à 07
A4: VOLUME PAR FAMILLE DE STRUCTURES
A5: Onglet | B5: Structures | C5: À contacter | D5: RDV pris | E5: Contrats signés | F5: Taux de signature
A6: 01 Communes & CCAS | B6: 12 | C6: =COUNTIF('01 Communes & CCAS'!$T$5:$T$400,"A contacter") | D6: =COUNTIF('01 Communes & CCAS'!$T$5:$T$400,"RDV pris") | E6: =COUNTIF('01 Communes & CCAS'!$T$5:$T$400,"Contrat signé") | F6: =IF(B6=0,"",E6/B6)
A7: 02 Intercommunalités | B7: 4 | C7: =COUNTIF('02 Intercommunalités'!$T$5:$T$400,"A contacter") | D7: =COUNTIF('02 Intercommunalités'!$T$5:$T$400,"RDV pris") | E7: =COUNTIF('02 Intercommunalités'!$T$5:$T$400,"Contrat signé") | F7: =IF(B7=0,"",E7/B7)
A8: 03 Département, Région & État | B8: 6 | C8: =COUNTIF('03 Département, Région & État'!$T$5:$T$400,"A contacter") | D8: =COUNTIF('03 Département, Région & État'!$T$5:$T$400,"RDV pris") | E8: =COUNTIF('03 Département, Région & État'!$T$5:$T$400,"Contrat signé") | F8: =IF(B8=0,"",E8/B8)
A9: 04 Lycées & collèges | B9: 6 | C9: =COUNTIF('04 Lycées & collèges'!$T$5:$T$400,"A contacter") | D9: =COUNTIF('04 Lycées & collèges'!$T$5:$T$400,"RDV pris") | E9: =COUNTIF('04 Lycées & collèges'!$T$5:$T$400,"Contrat signé") | F9: =IF(B9=0,"",E9/B9)
A10: 05 Hôpital public | B10: 3 | C10: =COUNTIF('05 Hôpital public'!$T$5:$T$400,"A contacter") | D10: =COUNTIF('05 Hôpital public'!$T$5:$T$400,"RDV pris") | E10: =COUNTIF('05 Hôpital public'!$T$5:$T$400,"Contrat signé") | F10: =IF(B10=0,"",E10/B10)
A11: 06 Cliniques & santé privée | B11: 4 | C11: =COUNTIF('06 Cliniques & santé privée'!$T$5:$T$400,"A contacter") | D11: =COUNTIF('06 Cliniques & santé privée'!$T$5:$T$400,"RDV pris") | E11: =COUNTIF('06 Cliniques & santé privée'!$T$5:$T$400,"Contrat signé") | F11: =IF(B11=0,"",E11/B11)
A12: 07 EHPAD & médico-social | B12: 4 | C12: =COUNTIF('07 EHPAD & médico-social'!$T$5:$T$400,"A contacter") | D12: =COUNTIF('07 EHPAD & médico-social'!$T$5:$T$400,"RDV pris") | E12: =COUNTIF('07 EHPAD & médico-social'!$T$5:$T$400,"Contrat signé") | F12: =IF(B12=0,"",E12/B12)
A13: TOTAL SECTEUR PUBLIC & SANTÉ | B13: =SUM(B6:B12) | C13: =SUM(C6:C12) | D13: =SUM(D6:D12) | E13: =SUM(E6:E12) | F13: =IF(B13=0,"",E13/B13)
A16: OBJECTIFS DE LA CAMPAGNE
A17: Structures à rencontrer / semaine | B17: 5
A18: Objectif recensement CNFPT | B18: toutes les collectivités P1 avant la campagne de janvier
A19: Offres d'apprentissage à collecter | B19: à définir
A20: Rappel | B20: dans le public, compter 3 mois entre l'accord oral et la signature

Sheet 09 Apprentissage dans le public
A1: L'APPRENTISSAGE DANS LE SECTEUR PUBLIC
A2: Ce qui change par rapport à une entreprise privée – à maîtriser avant le premier rendez-vous
A4: 1. TROIS FONCTIONS PUBLIQUES, TROIS RÈGLES
A5: Territoriale (FPT) | B5: Communes, CCAS, intercommunalités, Département, Région. C'est le CNFPT qui prend en charge les frais de formation.
A6: Hospitalière (FPH) | B6: CHU, GHER. Le CNFPT n'intervient PAS : le financement relève de l'établissement, avec l'appui possible de l'ANFH. À confirmer établissement par établissement.
A7: État (FPE) | B7: Rectorat, lycées et collèges, université. Financement porté par l'administration employeuse. À confirmer au cas par cas.
A8: Le privé de la santé | B8: Cliniques, dialyse, EHPAD associatifs : ce sont des employeurs PRIVÉS. On y applique les règles habituelles (OPCO, aides à l'embauche) — c'est souvent le circuit le plus rapide de tout ce fichier.
A9: 2. CE QUE FINANCE LE CNFPT (COLLECTIVITÉS)
A10: Le principe | B10: Le CNFPT prend en charge les frais de formation des apprentis des employeurs territoriaux. Pour 2026, il annonce le financement de 5 000 nouveaux contrats au niveau national.
A11: Les niveaux financés | B11: Niveaux 3 à 5, c'est-à-dire du CAP au BTS. Les niveaux 6 et 7 (licence, master) ne sont plus financés depuis 2025. Vos titres logistique sont donc dans la bonne fourchette : c'est un argument, utilisez-le.
A12: La condition n°1 | B12: L'employeur doit s'être RECENSÉ auprès du CNFPT pendant la campagne annuelle (celle de 2026 était ouverte du 19 janvier au 20 mars 2026). Pas de recensement = pas de financement, même avec un bon candidat.
A13: La condition n°2 | B13: Le métier visé doit figurer sur la liste des métiers en tension du CNFPT. VÉRIFIEZ que votre métier logistique y figure AVANT de promettre un financement à un DRH : c'est une promesse qui ne se rattrape pas.
A14: Les deux pièces à déposer | B14: ① l'APF (accord préalable de financement) : déposé par la collectivité dans les 3 mois qui précèdent le début du contrat. ② l'APC (demande de financement) : déposée par LE CFA dans le mois qui suit le démarrage. Cette deuxième pièce est de votre responsabilité — ne la laissez pas passer.
A15: À revérifier chaque année | B15: Les montants, les quotas et les dates de campagne changent d'une année sur l'autre. Ne citez jamais un chiffre sans l'avoir revérifié sur cnfpt.fr la semaine même.
A16: 3. LA CONSÉQUENCE : UN CALENDRIER INVERSÉ
A17: Le piège | B17: Dans le privé, on prospecte au printemps pour la rentrée. Dans le public territorial, si la collectivité ne s'est pas recensée en janvier-mars, la rentrée est déjà perdue pour le financement.
A18: Ce que ça change pour vous | B18: Vos rendez-vous d'octobre à décembre ne servent pas à signer : ils servent à faire inscrire la collectivité au recensement de janvier. Le closing, c'est « est-ce que je peux vous rappeler le 15 janvier pour votre recensement ? » — pas « est-ce que vous prenez un apprenti ? ».
A19: Et si la campagne est passée | B19: Deux options : demander au CNFPT s'il reste des contrats finançables sur l'année en cours, et surtout sécuriser l'intention pour la campagne suivante. Notez la date de rappel dans la colonne U de l'onglet concerné.
A20: 4. LES DÉLAIS ADMINISTRATIFS À ANTICIPER
A21: Ce qui prend du temps | B21: Inscription du poste au tableau des effectifs, délibération ou décision de l'exécutif, avis des instances, visa du comptable public. Comptez 3 mois entre l'accord oral et la signature — c'est normal, ce n'est pas un refus.
A22: Comment le gérer | B22: Faites du délai un argument : « je vous sollicite maintenant justement parce que je sais qu'il vous faut passer par une délibération ».
A23: 5. LES OBJECTIONS SPÉCIFIQUES AU PUBLIC
A24: « Nous n'avons pas de budget » | B24: « Les frais de formation ne sortent pas de votre budget : le CNFPT les prend en charge pour les niveaux CAP à BTS. Il vous reste la rémunération de l'apprenti, la plus basse du marché du travail. »
A25: « Il faut une délibération » | B25: « Exactement, et c'est pour ça que je viens maintenant et pas en juillet. Je vous prépare la fiche de poste et le calendrier, vous n'avez plus qu'à la passer. »
A26: « On ne pourra pas le garder après » | B26: Soyez honnête : l'apprentissage n'ouvre PAS droit à titularisation automatique — il faut le concours. Mais l'apprenti devient un candidat déjà formé à vos process, recrutable en contractuel, et prêt pour le concours. Un dispositif spécifique de titularisation existe pour les apprentis en situation de handicap : à vérifier au cas par cas.
A27: « Nous n'avons pas de tuteur » | B27: « Votre magasinier ou votre agent d'économat en est un. Je le forme et je l'accompagne, c'est compris dans notre accompagnement. »
A28: 6. VOS TROIS MEILLEURS ARGUMENTS DANS LE PUBLIC
A29: ① La transmission avant les départs | B29: Les magasiniers et agents d'économat partent en retraite et les savoirs partent avec eux. L'apprentissage est le seul moyen de transmettre avant le départ.
A30: ② L'emploi des jeunes du territoire | B30: Un élu entend cet argument mieux que n'importe quel autre : vos candidats habitent la commune, et beaucoup n'ont pas de moyen de locomotion pour aller travailler ailleurs. À Sainte-Rose, Salazie ou La Plaine, la collectivité est parfois le seul employeur accessible.
A31: ③ Le coût maîtrisé | B31: Formation prise en charge pour les niveaux CAP à BTS, rémunération réduite, aucun coût de recrutement. À condition d'avoir fait le recensement.

Sheet 10 Script d'appel (public)
A1: SCRIPT D'APPEL – COLLECTIVITÉS, ÉCOLES ET SANTÉ
A2: On ne parle pas à une mairie comme à un transporteur
A4: 1. TROUVER LA BONNE PORTE
A5: Commune / CCAS | B5: Demandez le DGS (directeur général des services) OU le directeur des services techniques. Formule : « je cherche la personne qui gère le magasin communal et les approvisionnements ».
A6: Lycée / collège | B6: Demandez l'ADJOINT GESTIONNAIRE. C'est lui qui tient le magasin, la demi-pension et les commandes. Ne demandez pas le proviseur en premier.
A7: Hôpital / CHU | B7: Demandez la direction des achats et de la logistique, puis la DRH. Le cadre du magasin général est celui qui dira « j'en ai besoin ».
A8: Clinique / EHPAD | B8: Demandez la DRH, le pharmacien gérant ou le responsable des services économiques. Dans un EHPAD, le directeur décide seul : c'est le circuit le plus court.
A9: 2. L'ACCROCHE (30 SECONDES)
A10: Phrase | B10: « Bonjour, [Prénom Nom], chargé des relations entreprises au CFA [nom]. Je ne vous appelle pas pour vous vendre une formation : je forme des jeunes de 16 à 25 ans aux métiers de la logistique sur le Nord-Est, et je cherche des structures qui ont un magasin ou un économat. Vous avez déjà accueilli un apprenti ? »
A11: Pourquoi ça marche | B11: On annonce qu'on ne vend rien (essentiel dans le public, où l'on se méfie du démarchage), on nomme le territoire, et on termine par une question ouverte.
A12: 3. LA QUESTION QUI QUALIFIE EN 30 SECONDES
A13: À poser tôt | B13: « Qui réceptionne vos livraisons et qui tient votre stock aujourd'hui ? »
A14: Ce que ça vous dit | B14: S'il y a une personne identifiée, il y a un poste ET un tuteur. Si la réponse est « tout le monde un peu », il y a un besoin d'organisation : c'est encore un meilleur argument.
A15: 4. LE CLOSING SPÉCIFIQUE AU PUBLIC
A16: Ne cherchez pas à signer | B16: Dans une collectivité, le premier appel ne se conclut jamais par une signature. Il se conclut par une DATE et un ENGAGEMENT DE RECENSEMENT.
A17: Phrase de closing | B17: « Je vous propose qu'on se voie 20 minutes. L'objectif : que vous soyez inscrit au recensement CNFPT de janvier, pour garder la porte ouverte. Ça ne vous engage à rien et ça vous coûte zéro. »
A18: À noter systématiquement | B18: La date de rappel dans la colonne U, et l'état du recensement dans la colonne V (Notes). C'est votre indicateur n°1 de septembre à janvier.
A19: 5. APRÈS L'APPEL – LE MÊME JOUR
A20: Traçabilité | B20: Colonnes « Statut prospection », « Date dernier contact » et « Notes ».
A21: L'email qui vous démarque | B21: Envoyez sous 2h : la fiche de poste type de l'apprenti logistique, le calendrier CNFPT, et votre date de rappel. Un DRH de collectivité qui reçoit un calendrier propre vous rappelle.

Sheet 11 Sources & mise à jour
A1: SOURCES DES DONNÉES
A2: Traçabilité et outils pour compléter / actualiser le fichier
A4: SOURCES UTILISÉES POUR CONSTRUIRE CE FICHIER
A5: Annuaire des Entreprises (INSEE) – y compris collectivités | B5: https://annuaire-entreprises.data.gouv.fr/
A6: CNFPT – financement des contrats d'apprentissage | B6: https://www.cnfpt.fr/s-informer/nos-actualites/le-fil-dactu/financement-contrats-dapprentissage/national
A7: CNFPT – accueillir un apprenti dans une collectivité | B7: https://www.cnfpt.fr/se-former/accueillir-apprenti/lapprentissage-collectivites-territoriales
A8: Annuaire de l'administration (Service-Public) | B8: https://lannuaire.service-public.gouv.fr/la-reunion/la-reunion
A9: Annuaire de l'éducation (établissements scolaires) | B9: https://data.education.gouv.fr/explore/dataset/fr-en-annuaire-education/
A10: Santé.fr – annuaire des établissements de santé (FINESS) | B10: https://www.sante.fr/
A11: CIREST – communauté intercommunale Réunion Est | B11: https://www.cirest.fr/qui-sommes-nous/
A12: CHU de La Réunion | B12: https://www.chu-reunion.fr/contact/
A13: Groupe de santé Clinifutur | B13: https://www.clinifutur.net/
A14: AURAR – centres de dialyse | B14: https://aurar.fr/nous-trouver/
A16: LIMITES CONNUES
A17: • Les NOMS des structures sont publics et fiables. Les ADRESSES proviennent de sources publiques et doivent être confirmées : la colonne « Fiabilité donnée » indique le niveau de confiance de chaque ligne.
A18: • Les règles de financement CNFPT (montants, quotas, dates de campagne, liste des métiers en tension) changent chaque année. Revérifiez sur cnfpt.fr avant d'annoncer quoi que ce soit à un employeur.
A19: • Les lignes « à lister » (autres lycées et collèges, EHPAD, ESAT, autres cliniques du groupe) sont des méthodes de recherche, pas des structures : à vous de les déplier commune par commune.
A20: • Le GHER (Saint-Benoît) figure aussi dans le fichier de prospection logistique privée : un seul appel, pas deux.
A21: • L'EPSMR est situé à Saint-Paul, hors du bassin Nord-Est : il n'est là que pour un candidat mobile.
